{
  "id": "cme9xpf5800038wpwm6mwapjl",
  "testId": "cme216bqg000f8wg08lorykq7",
  "testName": "HumaniQ QI – Quociente de Inteligência",
  "testType": "PERSONALITY",
  "userId": "cme9aryqs00018w88ivmnluxf",
  "sessionId": "cme9xpef800018wpwdj07rzqc",
  "overallScore": 145,
  "dimensionScores": {
    "Raciocínio Lógico": 100,
    "Raciocínio Numérico": 100,
    "Raciocínio Verbal": 100,
    "Raciocínio Espacial": 100
  },
  "duration": 30,
  "completedAt": "2025-08-13T12:16:11.756Z",
  "status": "completed",
  "metadata": {
    "testName": "HumaniQ QI – Quociente de Inteligência",
    "totalQuestions": 20,
    "completedAt": "2025-08-13T12:16:10.845Z",
    "calculationDate": "2025-08-13T12:16:11.754Z",
    "totalAnswers": 16,
    "testDescription": "Avalia habilidades cognitivas, raciocínio lógico e capacidade de resolução de problemas.",
    "archivedFromAPI": true
  },
  "archivedAt": "2025-08-13T12:16:11.770Z",
  "filePath": "C:\\Users\\ALICEBELLA\\Desktop\\HMNQV2\\app\\archives\\results\\2025\\08\\PERSONALITY\\cme9aryqs00018w88ivmnluxf_PERSONALITY_cme216bqg000f8wg08lorykq7_2025-08-13_12-16-11-756Z.json"
}